jupyterlab_collaborative_input/__init__.py
jupyterlab_collaborative_input/_version.py
jupyterlab_collaborative_input/labextension/build_log.json
jupyterlab_collaborative_input/labextension/package.json
jupyterlab_collaborative_input/labextension/static/lib_index_js.d02bd7f0b56d37a7d178.js
jupyterlab_collaborative_input/labextension/static/lib_index_js.d02bd7f0b56d37a7d178.js.map
jupyterlab_collaborative_input/labextension/static/remoteEntry.a99773b513a24472507d.js
jupyterlab_collaborative_input/labextension/static/remoteEntry.a99773b513a24472507d.js.map
jupyterlab_collaborative_input/labextension/static/style.js
jupyterlab_collaborative_input/labextension/static/style_index_js.45069f1d634e488f099f.js
jupyterlab_collaborative_input-0.1.0.data/data/share/jupyter/labextensions/jupyterlab-collaborative-input/build_log.json
jupyterlab_collaborative_input-0.1.0.data/data/share/jupyter/labextensions/jupyterlab-collaborative-input/install.json
jupyterlab_collaborative_input-0.1.0.data/data/share/jupyter/labextensions/jupyterlab-collaborative-input/package.json
jupyterlab_collaborative_input-0.1.0.data/data/share/jupyter/labextensions/jupyterlab-collaborative-input/static/lib_index_js.d02bd7f0b56d37a7d178.js
jupyterlab_collaborative_input-0.1.0.data/data/share/jupyter/labextensions/jupyterlab-collaborative-input/static/lib_index_js.d02bd7f0b56d37a7d178.js.map
jupyterlab_collaborative_input-0.1.0.data/data/share/jupyter/labextensions/jupyterlab-collaborative-input/static/remoteEntry.a99773b513a24472507d.js
jupyterlab_collaborative_input-0.1.0.data/data/share/jupyter/labextensions/jupyterlab-collaborative-input/static/remoteEntry.a99773b513a24472507d.js.map
jupyterlab_collaborative_input-0.1.0.data/data/share/jupyter/labextensions/jupyterlab-collaborative-input/static/style.js
jupyterlab_collaborative_input-0.1.0.data/data/share/jupyter/labextensions/jupyterlab-collaborative-input/static/style_index_js.45069f1d634e488f099f.js
jupyterlab_collaborative_input-0.1.0.dist-info/LICENSE.txt
jupyterlab_collaborative_input-0.1.0.dist-info/METADATA
jupyterlab_collaborative_input-0.1.0.dist-info/WHEEL
jupyterlab_collaborative_input-0.1.0.dist-info/top_level.txt
jupyterlab_collaborative_input-0.1.0.dist-info/RECORD
